JsonReader_heureka_code/__init__.py
JsonReader_heureka_code/__jsonReader.py
JsonReader_heureka_code-0.0.5.dist-info/LICENSE.txt
JsonReader_heureka_code-0.0.5.dist-info/METADATA
JsonReader_heureka_code-0.0.5.dist-info/WHEEL
JsonReader_heureka_code-0.0.5.dist-info/top_level.txt
JsonReader_heureka_code-0.0.5.dist-info/RECORD
