Metadata-Version: 2.1
Name: JsonReader-heureka-code
Version: 0.0.5
Summary: Verarbeitet JSON
Home-page: https://github.com/heureka-code/JsonReader-heureka-code
Author: heureka-code
License: MIT
Download-URL: https://github.com/heureka-code/JsonReader-heureka-code/archive/refs/tags/0.0.4.tar.gz
Platform: UNKNOWN
License-File: LICENSE.txt
